{
  "cli": {
    "version": ">= 1.0.0",
    "appVersionSource": "remote",
    "versionCode": 4
  },
  "build": {
    "development": {
      "developmentClient": true,
      "distribution": "internal",
      "android" : {
        "buildType": "apk"
      }
    },
    "SIT": {
      "developmentClient": false,
      "distribution": "internal",
      "android" : {
        "buildType": "apk"
      }
    },
    "UAT": {
      "developmentClient": false,
      "distribution": "internal",
      "android" : {
        "buildType": "apk"
      }
    },
    "review": {
      "developmentClient": false,
      "distribution": "internal",
      "android" : {
        "buildType": "apk"
      }
    },
    "production": {
      "autoIncrement": true,
      "developmentClient": false,
      "distribution": "store",
      "android" : {
        "buildType": "apk"
      }
    }
  },
  "submit": {
    "production": {}
  }
}
